pystylometry/README.md
pystylometry/__init__.py
pystylometry/_normalize.py
pystylometry/_types.py
pystylometry/_utils.py
pystylometry/authorship/README.md
pystylometry/authorship/__init__.py
pystylometry/authorship/additional_methods.py
pystylometry/authorship/burrows_delta.py
pystylometry/authorship/compression.py
pystylometry/authorship/kilgarriff.py
pystylometry/authorship/zeta.py
pystylometry/character/README.md
pystylometry/character/__init__.py
pystylometry/character/character_metrics.py
pystylometry/cli.py
pystylometry/consistency/README.md
pystylometry/consistency/__init__.py
pystylometry/consistency/_thresholds.py
pystylometry/consistency/drift.py
pystylometry/dialect/README.md
pystylometry/dialect/__init__.py
pystylometry/dialect/_data/dialect_markers.json
pystylometry/dialect/_loader.py
pystylometry/dialect/detector.py
pystylometry/lexical/README.md
pystylometry/lexical/__init__.py
pystylometry/lexical/advanced_diversity.py
pystylometry/lexical/function_words.py
pystylometry/lexical/hapax.py
pystylometry/lexical/mtld.py
pystylometry/lexical/repetition.py
pystylometry/lexical/ttr.py
pystylometry/lexical/word_frequency_sophistication.py
pystylometry/lexical/yule.py
pystylometry/ngrams/README.md
pystylometry/ngrams/__init__.py
pystylometry/ngrams/entropy.py
pystylometry/ngrams/extended_ngrams.py
pystylometry/prosody/README.md
pystylometry/prosody/__init__.py
pystylometry/prosody/rhythm_prosody.py
pystylometry/readability/README.md
pystylometry/readability/__init__.py
pystylometry/readability/additional_formulas.py
pystylometry/readability/ari.py
pystylometry/readability/coleman_liau.py
pystylometry/readability/complex_words.py
pystylometry/readability/flesch.py
pystylometry/readability/gunning_fog.py
pystylometry/readability/smog.py
pystylometry/readability/syllables.py
pystylometry/stylistic/README.md
pystylometry/stylistic/__init__.py
pystylometry/stylistic/cohesion_coherence.py
pystylometry/stylistic/genre_register.py
pystylometry/stylistic/markers.py
pystylometry-1.3.5.dist-info/LICENSE
pystylometry-1.3.5.dist-info/METADATA
pystylometry-1.3.5.dist-info/WHEEL
pystylometry-1.3.5.dist-info/entry_points.txt
pystylometry-1.3.5.dist-info/RECORD
