Metadata-Version: 2.1
Name: pystylometry
Version: 1.3.5
Summary: Comprehensive Python package for stylometric analysis
License: MIT
Keywords: stylometry,nlp,text-analysis,authorship,readability,lexical-diversity,readability-metrics
Author: Craig Trim
Author-email: craigtrim@gmail.com
Requires-Python: >=3.9,<4.0
Classifier: Development Status :: 5 - Production/Stable
Classifier: Intended Audience :: Developers
Classifier: Intended Audience :: Science/Research
Classifier: License :: OSI Approved :: MIT License
Classifier: Programming Language :: Python :: 3
Classifier: Programming Language :: Python :: 3.9
Classifier: Programming Language :: Python :: 3.10
Classifier: Programming Language :: Python :: 3.11
Classifier: Programming Language :: Python :: 3.12
Classifier: Topic :: Scientific/Engineering :: Information Analysis
Classifier: Topic :: Text Processing :: Linguistic
Classifier: Typing :: Typed
Project-URL: Homepage, https://github.com/craigtrim/pystylometry
Project-URL: Issues, https://github.com/craigtrim/pystylometry/issues
Project-URL: Repository, https://github.com/craigtrim/pystylometry
